{
  "DACA_Requests_by_FY": [
    {
      "Number of Form I-821D, Consideration of Deferred Action for Childhood Arrivals": "Requests by Intake and Case Status, by Fiscal Year",
      "__EMPTY": "",
      "__EMPTY_1": "",
      "__EMPTY_2": "",
      "__EMPTY_3": "",
      "__EMPTY_4": "",
      "__EMPTY_5": "",
      "__EMPTY_6": "",
      "__EMPTY_7": ""
    },
    {
      "Number of Form I-821D, Consideration of Deferred Action for Childhood Arrivals": "August 15, 2012 - June 30, 2025",
      "__EMPTY": "",
      "__EMPTY_1": "",
      "__EMPTY_2": "",
      "__EMPTY_3": "",
      "__EMPTY_4": "",
      "__EMPTY_5": "",
      "__EMPTY_6": "",
      "__EMPTY_7": ""
    },
    {
      "Number of Form I-821D, Consideration of Deferred Action for Childhood Arrivals": "",
      "__EMPTY": "Requests by Intake and Case Status",
      "__EMPTY_1": "",
      "__EMPTY_2": "",
      "__EMPTY_3": "",
      "__EMPTY_4": "",
      "__EMPTY_5": "",
      "__EMPTY_6": "",
      "__EMPTY_7": ""
    },
    {
      "Number of Form I-821D, Consideration of Deferred Action for Childhood Arrivals": "Period",
      "__EMPTY": "Requests Accepted1",
      "__EMPTY_1": "Requests Rejected2",
      "__EMPTY_2": "Total Requests Received3",
      "__EMPTY_3": "Approved4",
      "__EMPTY_4": "Denied5",
      "__EMPTY_5": "Pending6",
      "__EMPTY_6": "",
      "__EMPTY_7": ""
    },
    {
      "Number of Form I-821D, Consideration of Deferred Action for Childhood Arrivals": "Fiscal Year - Total",
      "__EMPTY": "",
      "__EMPTY_1": "",
      "__EMPTY_2": "",
      "__EMPTY_3": "",
      "__EMPTY_4": "",
      "__EMPTY_5": "",
      "__EMPTY_6": "",
      "__EMPTY_7": ""
    },
    {
      "Number of Form I-821D, Consideration of Deferred Action for Childhood Arrivals": "2012 Initial",
      "__EMPTY": 152430,
      "__EMPTY_1": 5396,
      "__EMPTY_2": 157826,
      "__EMPTY_3": 1684,
      "__EMPTY_4": 0,
      "__EMPTY_5": 150746,
      "__EMPTY_6": "",
      "__EMPTY_7": ""
    },
    {
      "Number of Form I-821D, Consideration of Deferred Action for Childhood Arrivals": "2013 Initial",
      "__EMPTY": 427611,
      "__EMPTY_1": 16355,
      "__EMPTY_2": 443966,
      "__EMPTY_3": 470596,
      "__EMPTY_4": 11019,
      "__EMPTY_5": 96729,
      "__EMPTY_6": "",
      "__EMPTY_7": ""
    },
    {
      "Number of Form I-821D, Consideration of Deferred Action for Childhood Arrivals": 2014,
      "__EMPTY": 238898,
      "__EMPTY_1": 24889,
      "__EMPTY_2": 263787,
      "__EMPTY_3": 158154,
      "__EMPTY_4": 21069,
      "__EMPTY_5": 156342,
      "__EMPTY_6": "",
      "__EMPTY_7": ""
    },
    {
      "Number of Form I-821D, Consideration of Deferred Action for Childhood Arrivals": "2014 Initial",
      "__EMPTY": 122474,
      "__EMPTY_1": 19064,
      "__EMPTY_2": 141538,
      "__EMPTY_3": 135920,
      "__EMPTY_4": 21066,
      "__EMPTY_5": 62157,
      "__EMPTY_6": "",
      "__EMPTY_7": ""
    },
    {
      "Number of Form I-821D, Consideration of Deferred Action for Childhood Arrivals": "2014 Renewal",
      "__EMPTY": 116424,
      "__EMPTY_1": 5825,
      "__EMPTY_2": 122249,
      "__EMPTY_3": 22234,
      "__EMPTY_4": 3,
      "__EMPTY_5": 94185,
      "__EMPTY_6": "",
      "__EMPTY_7": ""
    },
    {
      "Number of Form I-821D, Consideration of Deferred Action for Childhood Arrivals": 2015,
      "__EMPTY": 448846,
      "__EMPTY_1": 35502,
      "__EMPTY_2": 484348,
      "__EMPTY_3": 510329,
      "__EMPTY_4": 21437,
      "__EMPTY_5": 73324,
      "__EMPTY_6": "",
      "__EMPTY_7": ""
    },
    {
      "Number of Form I-821D, Consideration of Deferred Action for Childhood Arrivals": "2015 Initial",
      "__EMPTY": 85300,
      "__EMPTY_1": 7170,
      "__EMPTY_2": 92470,
      "__EMPTY_3": 90827,
      "__EMPTY_4": 19087,
      "__EMPTY_5": 37471,
      "__EMPTY_6": "",
      "__EMPTY_7": ""
    },
    {
      "Number of Form I-821D, Consideration of Deferred Action for Childhood Arrivals": "2015 Renewal",
      "__EMPTY": 363546,
      "__EMPTY_1": 28332,
      "__EMPTY_2": 391878,
      "__EMPTY_3": 419502,
      "__EMPTY_4": 2350,
      "__EMPTY_5": 35853,
      "__EMPTY_6": "",
      "__EMPTY_7": ""
    },
    {
      "Number of Form I-821D, Consideration of Deferred Action for Childhood Arrivals": 2016,
      "__EMPTY": 260701,
      "__EMPTY_1": 12317,
      "__EMPTY_2": 273018,
      "__EMPTY_3": 198809,
      "__EMPTY_4": 14551,
      "__EMPTY_5": 119789,
      "__EMPTY_6": "",
      "__EMPTY_7": ""
    },
    {
      "Number of Form I-821D, Consideration of Deferred Action for Childhood Arrivals": "2016 Initial",
      "__EMPTY": 73347,
      "__EMPTY_1": 1151,
      "__EMPTY_2": 74498,
      "__EMPTY_3": 52990,
      "__EMPTY_4": 11525,
      "__EMPTY_5": 45454,
      "__EMPTY_6": "",
      "__EMPTY_7": ""
    },
    {
      "Number of Form I-821D, Consideration of Deferred Action for Childhood Arrivals": "2016 Renewal",
      "__EMPTY": 187354,
      "__EMPTY_1": 11166,
      "__EMPTY_2": 198520,
      "__EMPTY_3": 145819,
      "__EMPTY_4": 3026,
      "__EMPTY_5": 74335,
      "__EMPTY_6": "",
      "__EMPTY_7": ""
    },
    {
      "Number of Form I-821D, Consideration of Deferred Action for Childhood Arrivals": 2017,
      "__EMPTY": 472850,
      "__EMPTY_1": 43455,
      "__EMPTY_2": 516305,
      "__EMPTY_3": 461908,
      "__EMPTY_4": 13190,
      "__EMPTY_5": 117453,
      "__EMPTY_6": "",
      "__EMPTY_7": ""
    },
    {
      "Number of Form I-821D, Consideration of Deferred Action for Childhood Arrivals": "2017 Initial",
      "__EMPTY": 45593,
      "__EMPTY_1": 44,
      "__EMPTY_2": 45637,
      "__EMPTY_3": 47132,
      "__EMPTY_4": 9161,
      "__EMPTY_5": 34701,
      "__EMPTY_6": "",
      "__EMPTY_7": ""
    },
    {
      "Number of Form I-821D, Consideration of Deferred Action for Childhood Arrivals": "2017 Renewal",
      "__EMPTY": 427257,
      "__EMPTY_1": 43411,
      "__EMPTY_2": 470668,
      "__EMPTY_3": 414776,
      "__EMPTY_4": 4029,
      "__EMPTY_5": 82752,
      "__EMPTY_6": "",
      "__EMPTY_7": ""
    },
    {
      "Number of Form I-821D, Consideration of Deferred Action for Childhood Arrivals": 2018,
      "__EMPTY": 260120,
      "__EMPTY_1": 29651,
      "__EMPTY_2": 289771,
      "__EMPTY_3": 319340,
      "__EMPTY_4": 12533,
      "__EMPTY_5": 45665,
      "__EMPTY_6": "",
      "__EMPTY_7": ""
    },
    {
      "Number of Form I-821D, Consideration of Deferred Action for Childhood Arrivals": "2018 Initial",
      "__EMPTY": 2060,
      "__EMPTY_1": 2,
      "__EMPTY_2": 2062,
      "__EMPTY_3": 24381,
      "__EMPTY_4": 8248,
      "__EMPTY_5": 4120,
      "__EMPTY_6": "",
      "__EMPTY_7": ""
    },
    {
      "Number of Form I-821D, Consideration of Deferred Action for Childhood Arrivals": "2018 Renewal",
      "__EMPTY": 258060,
      "__EMPTY_1": 29649,
      "__EMPTY_2": 287709,
      "__EMPTY_3": 294959,
      "__EMPTY_4": 4285,
      "__EMPTY_5": 41545,
      "__EMPTY_6": "",
      "__EMPTY_7": ""
    },
    {
      "Number of Form I-821D, Consideration of Deferred Action for Childhood Arrivals": 2019,
      "__EMPTY": 386156,
      "__EMPTY_1": 22006,
      "__EMPTY_2": 408162,
      "__EMPTY_3": 387438,
      "__EMPTY_4": 4944,
      "__EMPTY_5": 39408,
      "__EMPTY_6": "",
      "__EMPTY_7": ""
    },
    {
      "Number of Form I-821D, Consideration of Deferred Action for Childhood Arrivals": "2019 Initial",
      "__EMPTY": 1570,
      "__EMPTY_1": 4,
      "__EMPTY_2": 1574,
      "__EMPTY_3": 1774,
      "__EMPTY_4": 1602,
      "__EMPTY_5": 2308,
      "__EMPTY_6": "",
      "__EMPTY_7": ""
    },
    {
      "Number of Form I-821D, Consideration of Deferred Action for Childhood Arrivals": "2019 Renewal",
      "__EMPTY": 384586,
      "__EMPTY_1": 22002,
      "__EMPTY_2": 406588,
      "__EMPTY_3": 385664,
      "__EMPTY_4": 3342,
      "__EMPTY_5": 37100,
      "__EMPTY_6": "",
      "__EMPTY_7": ""
    },
    {
      "Number of Form I-821D, Consideration of Deferred Action for Childhood Arrivals": 2020,
      "__EMPTY": 313939,
      "__EMPTY_1": 29994,
      "__EMPTY_2": 343933,
      "__EMPTY_3": 294655,
      "__EMPTY_4": 3998,
      "__EMPTY_5": 54677,
      "__EMPTY_6": "",
      "__EMPTY_7": ""
    },
    {
      "Number of Form I-821D, Consideration of Deferred Action for Childhood Arrivals": "2020 Initial",
      "__EMPTY": 4289,
      "__EMPTY_1": 6,
      "__EMPTY_2": 4295,
      "__EMPTY_3": 1792,
      "__EMPTY_4": 715,
      "__EMPTY_5": 4085,
      "__EMPTY_6": "",
      "__EMPTY_7": ""
    },
    {
      "Number of Form I-821D, Consideration of Deferred Action for Childhood Arrivals": "2020 Renewal",
      "__EMPTY": 309650,
      "__EMPTY_1": 29988,
      "__EMPTY_2": 339638,
      "__EMPTY_3": 292863,
      "__EMPTY_4": 3283,
      "__EMPTY_5": 50592,
      "__EMPTY_6": "",
      "__EMPTY_7": ""
    },
    {
      "Number of Form I-821D, Consideration of Deferred Action for Childhood Arrivals": 2021,
      "__EMPTY": 438936,
      "__EMPTY_1": 31700,
      "__EMPTY_2": 470636,
      "__EMPTY_3": 359207,
      "__EMPTY_4": 3799,
      "__EMPTY_5": 130594,
      "__EMPTY_6": "",
      "__EMPTY_7": ""
    },
    {
      "Number of Form I-821D, Consideration of Deferred Action for Childhood Arrivals": "2021 Initial",
      "__EMPTY": 94216,
      "__EMPTY_1": 109,
      "__EMPTY_2": 94325,
      "__EMPTY_3": 7993,
      "__EMPTY_4": 1122,
      "__EMPTY_5": 89185,
      "__EMPTY_6": "",
      "__EMPTY_7": ""
    },
    {
      "Number of Form I-821D, Consideration of Deferred Action for Childhood Arrivals": "2021 Renewal",
      "__EMPTY": 344720,
      "__EMPTY_1": 31591,
      "__EMPTY_2": 376311,
      "__EMPTY_3": 351214,
      "__EMPTY_4": 2677,
      "__EMPTY_5": 41409,
      "__EMPTY_6": "",
      "__EMPTY_7": ""
    },
    {
      "Number of Form I-821D, Consideration of Deferred Action for Childhood Arrivals": 2022,
      "__EMPTY": 286162,
      "__EMPTY_1": 18249,
      "__EMPTY_2": 304411,
      "__EMPTY_3": 295361,
      "__EMPTY_4": 2551,
      "__EMPTY_5": 118764,
      "__EMPTY_6": "",
      "__EMPTY_7": ""
    },
    {
      "Number of Form I-821D, Consideration of Deferred Action for Childhood Arrivals": "2022 Initial",
      "__EMPTY": 5459,
      "__EMPTY_1": 22,
      "__EMPTY_2": 5481,
      "__EMPTY_3": 2,
      "__EMPTY_4": 5,
      "__EMPTY_5": 94632,
      "__EMPTY_6": "",
      "__EMPTY_7": ""
    },
    {
      "Number of Form I-821D, Consideration of Deferred Action for Childhood Arrivals": "2022 Renewal",
      "__EMPTY": 280703,
      "__EMPTY_1": 18227,
      "__EMPTY_2": 298930,
      "__EMPTY_3": 295359,
      "__EMPTY_4": 2546,
      "__EMPTY_5": 24132,
      "__EMPTY_6": "",
      "__EMPTY_7": ""
    },
    {
      "Number of Form I-821D, Consideration of Deferred Action for Childhood Arrivals": 2023,
      "__EMPTY": 333384,
      "__EMPTY_1": 14004,
      "__EMPTY_2": 347388,
      "__EMPTY_3": 304277,
      "__EMPTY_4": 1721,
      "__EMPTY_5": 146081,
      "__EMPTY_6": "",
      "__EMPTY_7": ""
    },
    {
      "Number of Form I-821D, Consideration of Deferred Action for Childhood Arrivals": "2023 Initial",
      "__EMPTY": 3415,
      "__EMPTY_1": 22,
      "__EMPTY_2": 3437,
      "__EMPTY_3": 2,
      "__EMPTY_4": 8,
      "__EMPTY_5": 97983,
      "__EMPTY_6": "",
      "__EMPTY_7": ""
    },
    {
      "Number of Form I-821D, Consideration of Deferred Action for Childhood Arrivals": "2023 Renewal",
      "__EMPTY": 329969,
      "__EMPTY_1": 13982,
      "__EMPTY_2": 343951,
      "__EMPTY_3": 304275,
      "__EMPTY_4": 1713,
      "__EMPTY_5": 48098,
      "__EMPTY_6": "",
      "__EMPTY_7": ""
    },
    {
      "Number of Form I-821D, Consideration of Deferred Action for Childhood Arrivals": 2024,
      "__EMPTY": 264528,
      "__EMPTY_1": 15871,
      "__EMPTY_2": 280399,
      "__EMPTY_3": 289651,
      "__EMPTY_4": 1844,
      "__EMPTY_5": 119106,
      "__EMPTY_6": "",
      "__EMPTY_7": ""
    },
    {
      "Number of Form I-821D, Consideration of Deferred Action for Childhood Arrivals": "2024 Initial",
      "__EMPTY": 2354,
      "__EMPTY_1": 8,
      "__EMPTY_2": 2362,
      "__EMPTY_3": 0,
      "__EMPTY_4": 0,
      "__EMPTY_5": 100336,
      "__EMPTY_6": "",
      "__EMPTY_7": ""
    },
    {
      "Number of Form I-821D, Consideration of Deferred Action for Childhood Arrivals": "2024 Renewal",
      "__EMPTY": 262174,
      "__EMPTY_1": 15863,
      "__EMPTY_2": 278037,
      "__EMPTY_3": 289651,
      "__EMPTY_4": 1844,
      "__EMPTY_5": 18770,
      "__EMPTY_6": "",
      "__EMPTY_7": ""
    },
    {
      "Number of Form I-821D, Consideration of Deferred Action for Childhood Arrivals": 2025,
      "__EMPTY": 233864,
      "__EMPTY_1": 11484,
      "__EMPTY_2": 245348,
      "__EMPTY_3": 221398,
      "__EMPTY_4": 1362,
      "__EMPTY_5": 130207,
      "__EMPTY_6": "",
      "__EMPTY_7": ""
    },
    {
      "Number of Form I-821D, Consideration of Deferred Action for Childhood Arrivals": "2025 Initial",
      "__EMPTY": 2104,
      "__EMPTY_1": 16,
      "__EMPTY_2": 2120,
      "__EMPTY_3": 0,
      "__EMPTY_4": 1,
      "__EMPTY_5": 102438,
      "__EMPTY_6": "",
      "__EMPTY_7": ""
    },
    {
      "Number of Form I-821D, Consideration of Deferred Action for Childhood Arrivals": "2025 Renewal",
      "__EMPTY": 231760,
      "__EMPTY_1": 11468,
      "__EMPTY_2": 243228,
      "__EMPTY_3": 221398,
      "__EMPTY_4": 1361,
      "__EMPTY_5": 27769,
      "__EMPTY_6": "",
      "__EMPTY_7": ""
    },
    {
      "Number of Form I-821D, Consideration of Deferred Action for Childhood Arrivals": "Total Cumulative",
      "__EMPTY": 4518425,
      "__EMPTY_1": 310873,
      "__EMPTY_2": 4829298,
      "__EMPTY_3": 4272807,
      "__EMPTY_4": 114018,
      "__EMPTY_5": 130207,
      "__EMPTY_6": "",
      "__EMPTY_7": ""
    },
    {
      "Number of Form I-821D, Consideration of Deferred Action for Childhood Arrivals": "Total Cumulative Initial",
      "__EMPTY": 1022222,
      "__EMPTY_1": 49369,
      "__EMPTY_2": 1071591,
      "__EMPTY_3": 835093,
      "__EMPTY_4": 83559,
      "__EMPTY_5": 102438,
      "__EMPTY_6": "",
      "__EMPTY_7": ""
    },
    {
      "Number of Form I-821D, Consideration of Deferred Action for Childhood Arrivals": "Total Cumulative Renewal",
      "__EMPTY": 3496203,
      "__EMPTY_1": 261504,
      "__EMPTY_2": 3757707,
      "__EMPTY_3": 3437714,
      "__EMPTY_4": 30459,
      "__EMPTY_5": 27769,
      "__EMPTY_6": "",
      "__EMPTY_7": ""
    },
    {
      "Number of Form I-821D, Consideration of Deferred Action for Childhood Arrivals": "Table Key",
      "__EMPTY": "",
      "__EMPTY_1": "",
      "__EMPTY_2": "",
      "__EMPTY_3": "",
      "__EMPTY_4": "",
      "__EMPTY_5": "",
      "__EMPTY_6": "",
      "__EMPTY_7": ""
    },
    {
      "Number of Form I-821D, Consideration of Deferred Action for Childhood Arrivals": "- Represents zero or rounds to 0.0",
      "__EMPTY": "",
      "__EMPTY_1": "",
      "__EMPTY_2": "",
      "__EMPTY_3": "",
      "__EMPTY_4": "",
      "__EMPTY_5": "",
      "__EMPTY_6": "",
      "__EMPTY_7": ""
    },
    {
      "Number of Form I-821D, Consideration of Deferred Action for Childhood Arrivals": "References:",
      "__EMPTY": "",
      "__EMPTY_1": "",
      "__EMPTY_2": "",
      "__EMPTY_3": "",
      "__EMPTY_4": "",
      "__EMPTY_5": "",
      "__EMPTY_6": "",
      "__EMPTY_7": ""
    },
    {
      "Number of Form I-821D, Consideration of Deferred Action for Childhood Arrivals": "1The number of new requests accepted at a Lockbox during the reporting period.",
      "__EMPTY": "",
      "__EMPTY_1": "",
      "__EMPTY_2": "",
      "__EMPTY_3": "",
      "__EMPTY_4": "",
      "__EMPTY_5": "",
      "__EMPTY_6": "",
      "__EMPTY_7": ""
    },
    {
      "Number of Form I-821D, Consideration of Deferred Action for Childhood Arrivals": "2The number of requests rejected at a Lockbox during the reporting period.",
      "__EMPTY": "",
      "__EMPTY_1": "",
      "__EMPTY_2": "",
      "__EMPTY_3": "",
      "__EMPTY_4": "",
      "__EMPTY_5": "",
      "__EMPTY_6": "",
      "__EMPTY_7": ""
    },
    {
      "Number of Form I-821D, Consideration of Deferred Action for Childhood Arrivals": "3The number of requests received and entered into a case-tracking system during the reporting period.",
      "__EMPTY": "",
      "__EMPTY_1": "",
      "__EMPTY_2": "",
      "__EMPTY_3": "",
      "__EMPTY_4": "",
      "__EMPTY_5": "",
      "__EMPTY_6": "",
      "__EMPTY_7": ""
    },
    {
      "Number of Form I-821D, Consideration of Deferred Action for Childhood Arrivals": "4The number of requests approved during the reporting period. Initial request approvals after July 16, 2021 are reaffirmations of previous approvals.",
      "__EMPTY": "",
      "__EMPTY_1": "",
      "__EMPTY_2": "",
      "__EMPTY_3": "",
      "__EMPTY_4": "",
      "__EMPTY_5": "",
      "__EMPTY_6": "",
      "__EMPTY_7": ""
    },
    {
      "Number of Form I-821D, Consideration of Deferred Action for Childhood Arrivals": "5The number of requests denied during the reporting period. Initial request denials after July 16, 2021 are terminations, reaffirmations of previous denials, or administrative actions taken to close a case.",
      "__EMPTY": "",
      "__EMPTY_1": "",
      "__EMPTY_2": "",
      "__EMPTY_3": "",
      "__EMPTY_4": "",
      "__EMPTY_5": "",
      "__EMPTY_6": "",
      "__EMPTY_7": ""
    },
    {
      "Number of Form I-821D, Consideration of Deferred Action for Childhood Arrivals": "6 The number of applications awaiting a decision as of the end of the reporting period. Some actions taken on cases are not reflected in this report such as administrative closures and ",
      "__EMPTY": "",
      "__EMPTY_1": "",
      "__EMPTY_2": "",
      "__EMPTY_3": "",
      "__EMPTY_4": "",
      "__EMPTY_5": "",
      "__EMPTY_6": "",
      "__EMPTY_7": ""
    },
    {
      "Number of Form I-821D, Consideration of Deferred Action for Childhood Arrivals": " transfers between offices; thus the total pending counts cannot be calculated using data from previous reporting periods.",
      "__EMPTY": "",
      "__EMPTY_1": "",
      "__EMPTY_2": "",
      "__EMPTY_3": "",
      "__EMPTY_4": "",
      "__EMPTY_5": "",
      "__EMPTY_6": "",
      "__EMPTY_7": ""
    },
    {
      "Number of Form I-821D, Consideration of Deferred Action for Childhood Arrivals": "Notes:",
      "__EMPTY": "",
      "__EMPTY_1": "",
      "__EMPTY_2": "",
      "__EMPTY_3": "",
      "__EMPTY_4": "",
      "__EMPTY_5": "",
      "__EMPTY_6": "",
      "__EMPTY_7": ""
    },
    {
      "Number of Form I-821D, Consideration of Deferred Action for Childhood Arrivals": "1) Some requests approved, denied, or pending a decision may have been received in previous reporting periods. ",
      "__EMPTY": "",
      "__EMPTY_1": "",
      "__EMPTY_2": "",
      "__EMPTY_3": "",
      "__EMPTY_4": "",
      "__EMPTY_5": "",
      "__EMPTY_6": "",
      "__EMPTY_7": ""
    },
    {
      "Number of Form I-821D, Consideration of Deferred Action for Childhood Arrivals": "2) The report reflects the most up-to-date estimate available at the time the report is generated.",
      "__EMPTY": "",
      "__EMPTY_1": "",
      "__EMPTY_2": "",
      "__EMPTY_3": "",
      "__EMPTY_4": "",
      "__EMPTY_5": "",
      "__EMPTY_6": "",
      "__EMPTY_7": ""
    },
    {
      "Number of Form I-821D, Consideration of Deferred Action for Childhood Arrivals": "3) The Quarterly Report totals may not match the totals provided within the Demographics Reports due to differences in how the data is generated.",
      "__EMPTY": "",
      "__EMPTY_1": "",
      "__EMPTY_2": "",
      "__EMPTY_3": "",
      "__EMPTY_4": "",
      "__EMPTY_5": "",
      "__EMPTY_6": "",
      "__EMPTY_7": ""
    },
    {
      "Number of Form I-821D, Consideration of Deferred Action for Childhood Arrivals": "4) For a complete list of USCIS forms and descriptions, visit: https://www.uscis.gov/forms",
      "__EMPTY": "",
      "__EMPTY_1": "",
      "__EMPTY_2": "",
      "__EMPTY_3": "",
      "__EMPTY_4": "",
      "__EMPTY_5": "",
      "__EMPTY_6": "",
      "__EMPTY_7": ""
    },
    {
      "Number of Form I-821D, Consideration of Deferred Action for Childhood Arrivals": "Source:",
      "__EMPTY": "",
      "__EMPTY_1": "",
      "__EMPTY_2": "",
      "__EMPTY_3": "",
      "__EMPTY_4": "",
      "__EMPTY_5": "",
      "__EMPTY_6": "",
      "__EMPTY_7": ""
    },
    {
      "Number of Form I-821D, Consideration of Deferred Action for Childhood Arrivals": "Department of Homeland Security, U.S. Citizenship and Immigration Services, Office of Performance and Quality",
      "__EMPTY": "",
      "__EMPTY_1": "",
      "__EMPTY_2": "",
      "__EMPTY_3": "",
      "__EMPTY_4": "",
      "__EMPTY_5": "",
      "__EMPTY_6": "",
      "__EMPTY_7": ""
    },
    {
      "Number of Form I-821D, Consideration of Deferred Action for Childhood Arrivals": "CLAIMS3, ELIS, accessed 7/2025, PAER0018275",
      "__EMPTY": "",
      "__EMPTY_1": "",
      "__EMPTY_2": "",
      "__EMPTY_3": "",
      "__EMPTY_4": "",
      "__EMPTY_5": "",
      "__EMPTY_6": "",
      "__EMPTY_7": ""
    }
  ],
  "DACA_FY25_Requests_by_Quarter": [
    {
      "Number of Form I-821D, Consideration of Deferred Action for Childhood Arrivals": "Requests by Intake and Case Status, Current Fiscal Year by Quarter",
      "__EMPTY": "",
      "__EMPTY_1": "",
      "__EMPTY_2": "",
      "__EMPTY_3": "",
      "__EMPTY_4": "",
      "__EMPTY_5": ""
    },
    {
      "Number of Form I-821D, Consideration of Deferred Action for Childhood Arrivals": "August 15, 2012 - June 30, 2025",
      "__EMPTY": "",
      "__EMPTY_1": "",
      "__EMPTY_2": "",
      "__EMPTY_3": "",
      "__EMPTY_4": "",
      "__EMPTY_5": ""
    },
    {
      "Number of Form I-821D, Consideration of Deferred Action for Childhood Arrivals": "",
      "__EMPTY": "Requests by Intake and Case Status",
      "__EMPTY_1": "",
      "__EMPTY_2": "",
      "__EMPTY_3": "",
      "__EMPTY_4": "",
      "__EMPTY_5": ""
    },
    {
      "Number of Form I-821D, Consideration of Deferred Action for Childhood Arrivals": "Period",
      "__EMPTY": "Requests Accepted1",
      "__EMPTY_1": "Requests Rejected2",
      "__EMPTY_2": "Total Requests Received3",
      "__EMPTY_3": "Approved4",
      "__EMPTY_4": "Denied5",
      "__EMPTY_5": "Pending6"
    },
    {
      "Number of Form I-821D, Consideration of Deferred Action for Childhood Arrivals": "Fiscal Year 2025 by Quarter",
      "__EMPTY": "",
      "__EMPTY_1": "",
      "__EMPTY_2": "",
      "__EMPTY_3": "",
      "__EMPTY_4": "",
      "__EMPTY_5": ""
    },
    {
      "Number of Form I-821D, Consideration of Deferred Action for Childhood Arrivals": "Q1. October - December",
      "__EMPTY": 72141,
      "__EMPTY_1": 3659,
      "__EMPTY_2": 75800,
      "__EMPTY_3": 69379,
      "__EMPTY_4": 482,
      "__EMPTY_5": 121385
    },
    {
      "Number of Form I-821D, Consideration of Deferred Action for Childhood Arrivals": "Q1. October - December Initial",
      "__EMPTY": 663,
      "__EMPTY_1": 4,
      "__EMPTY_2": 667,
      "__EMPTY_3": 0,
      "__EMPTY_4": 0,
      "__EMPTY_5": 100998
    },
    {
      "Number of Form I-821D, Consideration of Deferred Action for Childhood Arrivals": "Q1. October - December Renewal",
      "__EMPTY": 71478,
      "__EMPTY_1": 3655,
      "__EMPTY_2": 75133,
      "__EMPTY_3": 69379,
      "__EMPTY_4": 482,
      "__EMPTY_5": 20387
    },
    {
      "Number of Form I-821D, Consideration of Deferred Action for Childhood Arrivals": "Q2. January - March",
      "__EMPTY": 93307,
      "__EMPTY_1": 3943,
      "__EMPTY_2": 97250,
      "__EMPTY_3": 75525,
      "__EMPTY_4": 369,
      "__EMPTY_5": 138798
    },
    {
      "Number of Form I-821D, Consideration of Deferred Action for Childhood Arrivals": "Q2. January - March Initial",
      "__EMPTY": 862,
      "__EMPTY_1": 10,
      "__EMPTY_2": 872,
      "__EMPTY_3": 0,
      "__EMPTY_4": 1,
      "__EMPTY_5": 101859
    },
    {
      "Number of Form I-821D, Consideration of Deferred Action for Childhood Arrivals": "Q2. January - March Renewal",
      "__EMPTY": 92445,
      "__EMPTY_1": 3933,
      "__EMPTY_2": 96378,
      "__EMPTY_3": 75525,
      "__EMPTY_4": 368,
      "__EMPTY_5": 36939
    },
    {
      "Number of Form I-821D, Consideration of Deferred Action for Childhood Arrivals": "Q3. April - June",
      "__EMPTY": 68416,
      "__EMPTY_1": 3882,
      "__EMPTY_2": 72298,
      "__EMPTY_3": 76494,
      "__EMPTY_4": 511,
      "__EMPTY_5": 130207
    },
    {
      "Number of Form I-821D, Consideration of Deferred Action for Childhood Arrivals": "Q3. April - June Initial",
      "__EMPTY": 579,
      "__EMPTY_1": 2,
      "__EMPTY_2": 581,
      "__EMPTY_3": 0,
      "__EMPTY_4": 0,
      "__EMPTY_5": 102438
    },
    {
      "Number of Form I-821D, Consideration of Deferred Action for Childhood Arrivals": "Q3. April - June Renewal",
      "__EMPTY": 67837,
      "__EMPTY_1": 3880,
      "__EMPTY_2": 71717,
      "__EMPTY_3": 76494,
      "__EMPTY_4": 511,
      "__EMPTY_5": 27769
    },
    {
      "Number of Form I-821D, Consideration of Deferred Action for Childhood Arrivals": "Total",
      "__EMPTY": 233864,
      "__EMPTY_1": 11484,
      "__EMPTY_2": 245348,
      "__EMPTY_3": 221398,
      "__EMPTY_4": 1362,
      "__EMPTY_5": 130207
    },
    {
      "Number of Form I-821D, Consideration of Deferred Action for Childhood Arrivals": "Table Key",
      "__EMPTY": "",
      "__EMPTY_1": "",
      "__EMPTY_2": "",
      "__EMPTY_3": "",
      "__EMPTY_4": "",
      "__EMPTY_5": ""
    },
    {
      "Number of Form I-821D, Consideration of Deferred Action for Childhood Arrivals": "- Represents zero or rounds to 0.0",
      "__EMPTY": "",
      "__EMPTY_1": "",
      "__EMPTY_2": "",
      "__EMPTY_3": "",
      "__EMPTY_4": "",
      "__EMPTY_5": ""
    },
    {
      "Number of Form I-821D, Consideration of Deferred Action for Childhood Arrivals": "References:",
      "__EMPTY": "",
      "__EMPTY_1": "",
      "__EMPTY_2": "",
      "__EMPTY_3": "",
      "__EMPTY_4": "",
      "__EMPTY_5": ""
    },
    {
      "Number of Form I-821D, Consideration of Deferred Action for Childhood Arrivals": "1The number of new requests accepted at a Lockbox during the reporting period.",
      "__EMPTY": "",
      "__EMPTY_1": "",
      "__EMPTY_2": "",
      "__EMPTY_3": "",
      "__EMPTY_4": "",
      "__EMPTY_5": ""
    },
    {
      "Number of Form I-821D, Consideration of Deferred Action for Childhood Arrivals": "2The number of requests rejected at a Lockbox during the reporting period.",
      "__EMPTY": "",
      "__EMPTY_1": "",
      "__EMPTY_2": "",
      "__EMPTY_3": "",
      "__EMPTY_4": "",
      "__EMPTY_5": ""
    },
    {
      "Number of Form I-821D, Consideration of Deferred Action for Childhood Arrivals": "3The number of requests received and entered into a case-tracking system during the reporting period.",
      "__EMPTY": "",
      "__EMPTY_1": "",
      "__EMPTY_2": "",
      "__EMPTY_3": "",
      "__EMPTY_4": "",
      "__EMPTY_5": ""
    },
    {
      "Number of Form I-821D, Consideration of Deferred Action for Childhood Arrivals": "4The number of requests approved during the reporting period. Initial request approvals after July 16, 2021 are reaffirmations of previous approvals.",
      "__EMPTY": "",
      "__EMPTY_1": "",
      "__EMPTY_2": "",
      "__EMPTY_3": "",
      "__EMPTY_4": "",
      "__EMPTY_5": ""
    },
    {
      "Number of Form I-821D, Consideration of Deferred Action for Childhood Arrivals": "5The number of requests denied during the reporting period. Initial request denials after July 16, 2021 are terminations, reaffirmations of previous denials, or administrative actions taken to close a case.",
      "__EMPTY": "",
      "__EMPTY_1": "",
      "__EMPTY_2": "",
      "__EMPTY_3": "",
      "__EMPTY_4": "",
      "__EMPTY_5": ""
    },
    {
      "Number of Form I-821D, Consideration of Deferred Action for Childhood Arrivals": "6 The number of applications awaiting a decision as of the end of the reporting period. Some actions taken on cases are not reflected in this report such as administrative closures and ",
      "__EMPTY": "",
      "__EMPTY_1": "",
      "__EMPTY_2": "",
      "__EMPTY_3": "",
      "__EMPTY_4": "",
      "__EMPTY_5": ""
    },
    {
      "Number of Form I-821D, Consideration of Deferred Action for Childhood Arrivals": " transfers between offices; thus the total pending counts cannot be calculated using data from previous reporting periods.",
      "__EMPTY": "",
      "__EMPTY_1": "",
      "__EMPTY_2": "",
      "__EMPTY_3": "",
      "__EMPTY_4": "",
      "__EMPTY_5": ""
    },
    {
      "Number of Form I-821D, Consideration of Deferred Action for Childhood Arrivals": "Notes:",
      "__EMPTY": "",
      "__EMPTY_1": "",
      "__EMPTY_2": "",
      "__EMPTY_3": "",
      "__EMPTY_4": "",
      "__EMPTY_5": ""
    },
    {
      "Number of Form I-821D, Consideration of Deferred Action for Childhood Arrivals": "1) Some requests approved, denied, or pending a decision may have been received in previous reporting periods. ",
      "__EMPTY": "",
      "__EMPTY_1": "",
      "__EMPTY_2": "",
      "__EMPTY_3": "",
      "__EMPTY_4": "",
      "__EMPTY_5": ""
    },
    {
      "Number of Form I-821D, Consideration of Deferred Action for Childhood Arrivals": "2) The report reflects the most up-to-date estimate available at the time the report is generated.",
      "__EMPTY": "",
      "__EMPTY_1": "",
      "__EMPTY_2": "",
      "__EMPTY_3": "",
      "__EMPTY_4": "",
      "__EMPTY_5": ""
    },
    {
      "Number of Form I-821D, Consideration of Deferred Action for Childhood Arrivals": "3) The Quarterly Report totals may not match the totals provided within the Demographics Reports due to differences in how the data is generated.",
      "__EMPTY": "",
      "__EMPTY_1": "",
      "__EMPTY_2": "",
      "__EMPTY_3": "",
      "__EMPTY_4": "",
      "__EMPTY_5": ""
    },
    {
      "Number of Form I-821D, Consideration of Deferred Action for Childhood Arrivals": "4) For a complete list of USCIS forms and descriptions, visit: https://www.uscis.gov/forms",
      "__EMPTY": "",
      "__EMPTY_1": "",
      "__EMPTY_2": "",
      "__EMPTY_3": "",
      "__EMPTY_4": "",
      "__EMPTY_5": ""
    },
    {
      "Number of Form I-821D, Consideration of Deferred Action for Childhood Arrivals": "Source:",
      "__EMPTY": "",
      "__EMPTY_1": "",
      "__EMPTY_2": "",
      "__EMPTY_3": "",
      "__EMPTY_4": "",
      "__EMPTY_5": ""
    },
    {
      "Number of Form I-821D, Consideration of Deferred Action for Childhood Arrivals": "Department of Homeland Security, U.S. Citizenship and Immigration Services, Office of Performance and Quality",
      "__EMPTY": "",
      "__EMPTY_1": "",
      "__EMPTY_2": "",
      "__EMPTY_3": "",
      "__EMPTY_4": "",
      "__EMPTY_5": ""
    },
    {
      "Number of Form I-821D, Consideration of Deferred Action for Childhood Arrivals": "CLAIMS3, ELIS, accessed 7/2025, PAER0018275",
      "__EMPTY": "",
      "__EMPTY_1": "",
      "__EMPTY_2": "",
      "__EMPTY_3": "",
      "__EMPTY_4": "",
      "__EMPTY_5": ""
    }
  ],
  "DACA_COB": [
    {
      "Number of Form I-821D, Consideration of Deferred Action for Childhood Arrivals": "Accepted and Approved Requests by Country of Birth",
      "__EMPTY": "",
      "__EMPTY_1": "",
      "__EMPTY_2": "",
      "__EMPTY_3": "",
      "__EMPTY_4": "",
      "__EMPTY_5": ""
    },
    {
      "Number of Form I-821D, Consideration of Deferred Action for Childhood Arrivals": "August 15, 2012 - June 30, 2025",
      "__EMPTY": "",
      "__EMPTY_1": "",
      "__EMPTY_2": "",
      "__EMPTY_3": "",
      "__EMPTY_4": "",
      "__EMPTY_5": ""
    },
    {
      "Number of Form I-821D, Consideration of Deferred Action for Childhood Arrivals": "",
      "__EMPTY": "Accepted to Date1",
      "__EMPTY_1": "",
      "__EMPTY_2": "",
      "__EMPTY_3": "Approved to Date2",
      "__EMPTY_4": "",
      "__EMPTY_5": ""
    },
    {
      "Number of Form I-821D, Consideration of Deferred Action for Childhood Arrivals": "Top Countries of Birth",
      "__EMPTY": "Initials",
      "__EMPTY_1": "Renewals",
      "__EMPTY_2": "Total",
      "__EMPTY_3": "Initials",
      "__EMPTY_4": "Renewals",
      "__EMPTY_5": "Total"
    },
    {
      "Number of Form I-821D, Consideration of Deferred Action for Childhood Arrivals": "Country",
      "__EMPTY": "",
      "__EMPTY_1": "",
      "__EMPTY_2": "",
      "__EMPTY_3": "",
      "__EMPTY_4": "",
      "__EMPTY_5": ""
    },
    {
      "Number of Form I-821D, Consideration of Deferred Action for Childhood Arrivals": "Mexico",
      "__EMPTY": 802118,
      "__EMPTY_1": 2794581,
      "__EMPTY_2": 3596699,
      "__EMPTY_3": 658197,
      "__EMPTY_4": 2748172,
      "__EMPTY_5": 3406369
    },
    {
      "Number of Form I-821D, Consideration of Deferred Action for Childhood Arrivals": "El Salvador",
      "__EMPTY": 38404,
      "__EMPTY_1": 135223,
      "__EMPTY_2": 173627,
      "__EMPTY_3": 30007,
      "__EMPTY_4": 132563,
      "__EMPTY_5": 162570
    },
    {
      "Number of Form I-821D, Consideration of Deferred Action for Childhood Arrivals": "Guatemala",
      "__EMPTY": 28104,
      "__EMPTY_1": 90513,
      "__EMPTY_2": 118617,
      "__EMPTY_3": 21221,
      "__EMPTY_4": 88724,
      "__EMPTY_5": 109945
    },
    {
      "Number of Form I-821D, Consideration of Deferred Action for Childhood Arrivals": "Honduras",
      "__EMPTY": 25453,
      "__EMPTY_1": 83709,
      "__EMPTY_2": 109162,
      "__EMPTY_3": 19333,
      "__EMPTY_4": 81931,
      "__EMPTY_5": 101264
    },
    {
      "Number of Form I-821D, Consideration of Deferred Action for Childhood Arrivals": "Korea, South",
      "__EMPTY": 10061,
      "__EMPTY_1": 36968,
      "__EMPTY_2": 47029,
      "__EMPTY_3": 9052,
      "__EMPTY_4": 36528,
      "__EMPTY_5": 45580
    },
    {
      "Number of Form I-821D, Consideration of Deferred Action for Childhood Arrivals": "Peru",
      "__EMPTY": 10266,
      "__EMPTY_1": 36259,
      "__EMPTY_2": 46525,
      "__EMPTY_3": 9356,
      "__EMPTY_4": 35766,
      "__EMPTY_5": 45122
    },
    {
      "Number of Form I-821D, Consideration of Deferred Action for Childhood Arrivals": "Brazil",
      "__EMPTY": 9285,
      "__EMPTY_1": 28298,
      "__EMPTY_2": 37583,
      "__EMPTY_3": 7719,
      "__EMPTY_4": 27908,
      "__EMPTY_5": 35627
    },
    {
      "Number of Form I-821D, Consideration of Deferred Action for Childhood Arrivals": "Ecuador",
      "__EMPTY": 8256,
      "__EMPTY_1": 26602,
      "__EMPTY_2": 34858,
      "__EMPTY_3": 6916,
      "__EMPTY_4": 26104,
      "__EMPTY_5": 33020
    },
    {
      "Number of Form I-821D, Consideration of Deferred Action for Childhood Arrivals": "Colombia",
      "__EMPTY": 7630,
      "__EMPTY_1": 24413,
      "__EMPTY_2": 32043,
      "__EMPTY_3": 6780,
      "__EMPTY_4": 24067,
      "__EMPTY_5": 30847
    },
    {
      "Number of Form I-821D, Consideration of Deferred Action for Childhood Arrivals": "Philippines",
      "__EMPTY": 5458,
      "__EMPTY_1": 18903,
      "__EMPTY_2": 24361,
      "__EMPTY_3": 4837,
      "__EMPTY_4": 18766,
      "__EMPTY_5": 23603
    },
    {
      "Number of Form I-821D, Consideration of Deferred Action for Childhood Arrivals": "Argentina",
      "__EMPTY": 5527,
      "__EMPTY_1": 18489,
      "__EMPTY_2": 24016,
      "__EMPTY_3": 4977,
      "__EMPTY_4": 18265,
      "__EMPTY_5": 23242
    },
    {
      "Number of Form I-821D, Consideration of Deferred Action for Childhood Arrivals": "Jamaica",
      "__EMPTY": 4831,
      "__EMPTY_1": 12359,
      "__EMPTY_2": 17190,
      "__EMPTY_3": 3583,
      "__EMPTY_4": 12143,
      "__EMPTY_5": 15726
    },
    {
      "Number of Form I-821D, Consideration of Deferred Action for Childhood Arrivals": "India",
      "__EMPTY": 3974,
      "__EMPTY_1": 13024,
      "__EMPTY_2": 16998,
      "__EMPTY_3": 3288,
      "__EMPTY_4": 12800,
      "__EMPTY_5": 16088
    },
    {
      "Number of Form I-821D, Consideration of Deferred Action for Childhood Arrivals": "Venezuela",
      "__EMPTY": 3696,
      "__EMPTY_1": 11935,
      "__EMPTY_2": 15631,
      "__EMPTY_3": 3214,
      "__EMPTY_4": 11760,
      "__EMPTY_5": 14974
    },
    {
      "Number of Form I-821D, Consideration of Deferred Action for Childhood Arrivals": "Dominican Republic",
      "__EMPTY": 4239,
      "__EMPTY_1": 10671,
      "__EMPTY_2": 14910,
      "__EMPTY_3": 3307,
      "__EMPTY_4": 10499,
      "__EMPTY_5": 13806
    },
    {
      "Number of Form I-821D, Consideration of Deferred Action for Childhood Arrivals": "Uruguay",
      "__EMPTY": 2852,
      "__EMPTY_1": 9122,
      "__EMPTY_2": 11974,
      "__EMPTY_3": 2514,
      "__EMPTY_4": 9006,
      "__EMPTY_5": 11520
    },
    {
      "Number of Form I-821D, Consideration of Deferred Action for Childhood Arrivals": "Trinidad And Tobago",
      "__EMPTY": 3314,
      "__EMPTY_1": 8640,
      "__EMPTY_2": 11954,
      "__EMPTY_3": 2662,
      "__EMPTY_4": 8530,
      "__EMPTY_5": 11192
    },
    {
      "Number of Form I-821D, Consideration of Deferred Action for Childhood Arrivals": "Bolivia",
      "__EMPTY": 2355,
      "__EMPTY_1": 8187,
      "__EMPTY_2": 10542,
      "__EMPTY_3": 2133,
      "__EMPTY_4": 8077,
      "__EMPTY_5": 10210
    },
    {
      "Number of Form I-821D, Consideration of Deferred Action for Childhood Arrivals": "Costa Rica",
      "__EMPTY": 2443,
      "__EMPTY_1": 7679,
      "__EMPTY_2": 10122,
      "__EMPTY_3": 2114,
      "__EMPTY_4": 7566,
      "__EMPTY_5": 9680
    },
    {
      "Number of Form I-821D, Consideration of Deferred Action for Childhood Arrivals": "Nicaragua",
      "__EMPTY": 2140,
      "__EMPTY_1": 6857,
      "__EMPTY_2": 8997,
      "__EMPTY_3": 1692,
      "__EMPTY_4": 6745,
      "__EMPTY_5": 8437
    },
    {
      "Number of Form I-821D, Consideration of Deferred Action for Childhood Arrivals": "Chile",
      "__EMPTY": 2026,
      "__EMPTY_1": 6795,
      "__EMPTY_2": 8821,
      "__EMPTY_3": 1803,
      "__EMPTY_4": 6708,
      "__EMPTY_5": 8511
    },
    {
      "Number of Form I-821D, Consideration of Deferred Action for Childhood Arrivals": "Poland",
      "__EMPTY": 2174,
      "__EMPTY_1": 6462,
      "__EMPTY_2": 8636,
      "__EMPTY_3": 1890,
      "__EMPTY_4": 6383,
      "__EMPTY_5": 8273
    },
    {
      "Number of Form I-821D, Consideration of Deferred Action for Childhood Arrivals": "Pakistan",
      "__EMPTY": 2055,
      "__EMPTY_1": 6488,
      "__EMPTY_2": 8543,
      "__EMPTY_3": 1747,
      "__EMPTY_4": 6391,
      "__EMPTY_5": 8138
    },
    {
      "Number of Form I-821D, Consideration of Deferred Action for Childhood Arrivals": "Nigeria",
      "__EMPTY": 1740,
      "__EMPTY_1": 5083,
      "__EMPTY_2": 6823,
      "__EMPTY_3": 1348,
      "__EMPTY_4": 4961,
      "__EMPTY_5": 6309
    },
    {
      "Number of Form I-821D, Consideration of Deferred Action for Childhood Arrivals": "Guyana",
      "__EMPTY": 1586,
      "__EMPTY_1": 4733,
      "__EMPTY_2": 6319,
      "__EMPTY_3": 1317,
      "__EMPTY_4": 4655,
      "__EMPTY_5": 5972
    },
    {
      "Number of Form I-821D, Consideration of Deferred Action for Childhood Arrivals": "All Others",
      "__EMPTY": 32235,
      "__EMPTY_1": 84210,
      "__EMPTY_2": 116445,
      "__EMPTY_3": 24086,
      "__EMPTY_4": 82696,
      "__EMPTY_5": 106782
    },
    {
      "Number of Form I-821D, Consideration of Deferred Action for Childhood Arrivals": "Grand Total",
      "__EMPTY": 1022222,
      "__EMPTY_1": 3496203,
      "__EMPTY_2": 4518425,
      "__EMPTY_3": 835093,
      "__EMPTY_4": 3437714,
      "__EMPTY_5": 4272807
    },
    {
      "Number of Form I-821D, Consideration of Deferred Action for Childhood Arrivals": "Table Key",
      "__EMPTY": "",
      "__EMPTY_1": "",
      "__EMPTY_2": "",
      "__EMPTY_3": "",
      "__EMPTY_4": "",
      "__EMPTY_5": ""
    },
    {
      "Number of Form I-821D, Consideration of Deferred Action for Childhood Arrivals": "- Represents zero",
      "__EMPTY": "",
      "__EMPTY_1": "",
      "__EMPTY_2": "",
      "__EMPTY_3": "",
      "__EMPTY_4": "",
      "__EMPTY_5": ""
    },
    {
      "Number of Form I-821D, Consideration of Deferred Action for Childhood Arrivals": "References:",
      "__EMPTY": "",
      "__EMPTY_1": "",
      "__EMPTY_2": "",
      "__EMPTY_3": "",
      "__EMPTY_4": "",
      "__EMPTY_5": ""
    },
    {
      "Number of Form I-821D, Consideration of Deferred Action for Childhood Arrivals": "1 The number of requests accepted to date of the reporting period.",
      "__EMPTY": "",
      "__EMPTY_1": "",
      "__EMPTY_2": "",
      "__EMPTY_3": "",
      "__EMPTY_4": "",
      "__EMPTY_5": ""
    },
    {
      "Number of Form I-821D, Consideration of Deferred Action for Childhood Arrivals": "2  The number of requests approved to date of the reporting period.",
      "__EMPTY": "",
      "__EMPTY_1": "",
      "__EMPTY_2": "",
      "__EMPTY_3": "",
      "__EMPTY_4": "",
      "__EMPTY_5": ""
    },
    {
      "Number of Form I-821D, Consideration of Deferred Action for Childhood Arrivals": "3  All fields with a blank in the country of birth field are included in the field \"All Others.\"",
      "__EMPTY": "",
      "__EMPTY_1": "",
      "__EMPTY_2": "",
      "__EMPTY_3": "",
      "__EMPTY_4": "",
      "__EMPTY_5": ""
    },
    {
      "Number of Form I-821D, Consideration of Deferred Action for Childhood Arrivals": "Notes:",
      "__EMPTY": "",
      "__EMPTY_1": "",
      "__EMPTY_2": "",
      "__EMPTY_3": "",
      "__EMPTY_4": "",
      "__EMPTY_5": ""
    },
    {
      "Number of Form I-821D, Consideration of Deferred Action for Childhood Arrivals": "1) Some requests approved may have been received in previous reporting periods. ",
      "__EMPTY": "",
      "__EMPTY_1": "",
      "__EMPTY_2": "",
      "__EMPTY_3": "",
      "__EMPTY_4": "",
      "__EMPTY_5": ""
    },
    {
      "Number of Form I-821D, Consideration of Deferred Action for Childhood Arrivals": "2) The report reflects the most up-to-date estimate data available at the time the report is generated.",
      "__EMPTY": "",
      "__EMPTY_1": "",
      "__EMPTY_2": "",
      "__EMPTY_3": "",
      "__EMPTY_4": "",
      "__EMPTY_5": ""
    },
    {
      "Number of Form I-821D, Consideration of Deferred Action for Childhood Arrivals": "3) Ranked by total approvals.",
      "__EMPTY": "",
      "__EMPTY_1": "",
      "__EMPTY_2": "",
      "__EMPTY_3": "",
      "__EMPTY_4": "",
      "__EMPTY_5": ""
    },
    {
      "Number of Form I-821D, Consideration of Deferred Action for Childhood Arrivals": "4) For a complete list of USCIS forms and descriptions, visit: https://www.uscis.gov/forms",
      "__EMPTY": "",
      "__EMPTY_1": "",
      "__EMPTY_2": "",
      "__EMPTY_3": "",
      "__EMPTY_4": "",
      "__EMPTY_5": ""
    },
    {
      "Number of Form I-821D, Consideration of Deferred Action for Childhood Arrivals": "Source:",
      "__EMPTY": "",
      "__EMPTY_1": "",
      "__EMPTY_2": "",
      "__EMPTY_3": "",
      "__EMPTY_4": "",
      "__EMPTY_5": ""
    },
    {
      "Number of Form I-821D, Consideration of Deferred Action for Childhood Arrivals": "Department of Homeland Security, U.S. Citizenship and Immigration Services, Office of Performance and Quality",
      "__EMPTY": "",
      "__EMPTY_1": "",
      "__EMPTY_2": "",
      "__EMPTY_3": "",
      "__EMPTY_4": "",
      "__EMPTY_5": ""
    },
    {
      "Number of Form I-821D, Consideration of Deferred Action for Childhood Arrivals": "CLAIMS3, ELIS, accessed 7/2025, PAER0018275",
      "__EMPTY": "",
      "__EMPTY_1": "",
      "__EMPTY_2": "",
      "__EMPTY_3": "",
      "__EMPTY_4": "",
      "__EMPTY_5": ""
    }
  ],
  "DACA_State": [
    {
      "Number of Form I-821D, Consideration of Deferred Action for Childhood Arrivals": "Accepted and Approved Requests by State/Territory of Residence",
      "__EMPTY": "",
      "__EMPTY_1": "",
      "__EMPTY_2": "",
      "__EMPTY_3": "",
      "__EMPTY_4": "",
      "__EMPTY_5": ""
    },
    {
      "Number of Form I-821D, Consideration of Deferred Action for Childhood Arrivals": "August 15, 2012 - June 30, 2025",
      "__EMPTY": "",
      "__EMPTY_1": "",
      "__EMPTY_2": "",
      "__EMPTY_3": "",
      "__EMPTY_4": "",
      "__EMPTY_5": ""
    },
    {
      "Number of Form I-821D, Consideration of Deferred Action for Childhood Arrivals": "",
      "__EMPTY": "Accepted to Date1",
      "__EMPTY_1": "",
      "__EMPTY_2": "",
      "__EMPTY_3": "Approved to Date2",
      "__EMPTY_4": "",
      "__EMPTY_5": ""
    },
    {
      "Number of Form I-821D, Consideration of Deferred Action for Childhood Arrivals": "Residence",
      "__EMPTY": "Initials",
      "__EMPTY_1": "Renewals",
      "__EMPTY_2": "Total",
      "__EMPTY_3": "Initials",
      "__EMPTY_4": "Renewals",
      "__EMPTY_5": "Total"
    },
    {
      "Number of Form I-821D, Consideration of Deferred Action for Childhood Arrivals": "California",
      "__EMPTY": 289284,
      "__EMPTY_1": 989385,
      "__EMPTY_2": 1278669,
      "__EMPTY_3": 241146,
      "__EMPTY_4": 974079,
      "__EMPTY_5": 1215225
    },
    {
      "Number of Form I-821D, Consideration of Deferred Action for Childhood Arrivals": "Texas",
      "__EMPTY": 171459,
      "__EMPTY_1": 577423,
      "__EMPTY_2": 748882,
      "__EMPTY_3": 135836,
      "__EMPTY_4": 567930,
      "__EMPTY_5": 703766
    },
    {
      "Number of Form I-821D, Consideration of Deferred Action for Childhood Arrivals": "Illinois",
      "__EMPTY": 53792,
      "__EMPTY_1": 183479,
      "__EMPTY_2": 237271,
      "__EMPTY_3": 45500,
      "__EMPTY_4": 180774,
      "__EMPTY_5": 226274
    },
    {
      "Number of Form I-821D, Consideration of Deferred Action for Childhood Arrivals": "New York",
      "__EMPTY": 50326,
      "__EMPTY_1": 148052,
      "__EMPTY_2": 198378,
      "__EMPTY_3": 40947,
      "__EMPTY_4": 145604,
      "__EMPTY_5": 186551
    },
    {
      "Number of Form I-821D, Consideration of Deferred Action for Childhood Arrivals": "Florida",
      "__EMPTY": 42592,
      "__EMPTY_1": 136796,
      "__EMPTY_2": 179388,
      "__EMPTY_3": 32942,
      "__EMPTY_4": 134468,
      "__EMPTY_5": 167410
    },
    {
      "Number of Form I-821D, Consideration of Deferred Action for Childhood Arrivals": "Arizona",
      "__EMPTY": 37392,
      "__EMPTY_1": 132511,
      "__EMPTY_2": 169903,
      "__EMPTY_3": 30768,
      "__EMPTY_4": 129904,
      "__EMPTY_5": 160672
    },
    {
      "Number of Form I-821D, Consideration of Deferred Action for Childhood Arrivals": "North Carolina",
      "__EMPTY": 35263,
      "__EMPTY_1": 131772,
      "__EMPTY_2": 167035,
      "__EMPTY_3": 29919,
      "__EMPTY_4": 129618,
      "__EMPTY_5": 159537
    },
    {
      "Number of Form I-821D, Consideration of Deferred Action for Childhood Arrivals": "Georgia",
      "__EMPTY": 33720,
      "__EMPTY_1": 113749,
      "__EMPTY_2": 147469,
      "__EMPTY_3": 26046,
      "__EMPTY_4": 111334,
      "__EMPTY_5": 137380
    },
    {
      "Number of Form I-821D, Consideration of Deferred Action for Childhood Arrivals": "New Jersey",
      "__EMPTY": 27453,
      "__EMPTY_1": 88870,
      "__EMPTY_2": 116323,
      "__EMPTY_3": 22239,
      "__EMPTY_4": 87400,
      "__EMPTY_5": 109639
    },
    {
      "Number of Form I-821D, Consideration of Deferred Action for Childhood Arrivals": "Washington",
      "__EMPTY": 24589,
      "__EMPTY_1": 86292,
      "__EMPTY_2": 110881,
      "__EMPTY_3": 19623,
      "__EMPTY_4": 84901,
      "__EMPTY_5": 104524
    },
    {
      "Number of Form I-821D, Consideration of Deferred Action for Childhood Arrivals": "Colorado",
      "__EMPTY": 22687,
      "__EMPTY_1": 78939,
      "__EMPTY_2": 101626,
      "__EMPTY_3": 18756,
      "__EMPTY_4": 77462,
      "__EMPTY_5": 96218
    },
    {
      "Number of Form I-821D, Consideration of Deferred Action for Childhood Arrivals": "Nevada",
      "__EMPTY": 17388,
      "__EMPTY_1": 66913,
      "__EMPTY_2": 84301,
      "__EMPTY_3": 14471,
      "__EMPTY_4": 65950,
      "__EMPTY_5": 80421
    },
    {
      "Number of Form I-821D, Consideration of Deferred Action for Childhood Arrivals": "Virginia",
      "__EMPTY": 15059,
      "__EMPTY_1": 51921,
      "__EMPTY_2": 66980,
      "__EMPTY_3": 12452,
      "__EMPTY_4": 50901,
      "__EMPTY_5": 63353
    },
    {
      "Number of Form I-821D, Consideration of Deferred Action for Childhood Arrivals": "Oregon",
      "__EMPTY": 14115,
      "__EMPTY_1": 52836,
      "__EMPTY_2": 66951,
      "__EMPTY_3": 12192,
      "__EMPTY_4": 52034,
      "__EMPTY_5": 64226
    },
    {
      "Number of Form I-821D, Consideration of Deferred Action for Childhood Arrivals": "Indiana",
      "__EMPTY": 12969,
      "__EMPTY_1": 48261,
      "__EMPTY_2": 61230,
      "__EMPTY_3": 10885,
      "__EMPTY_4": 47457,
      "__EMPTY_5": 58342
    },
    {
      "Number of Form I-821D, Consideration of Deferred Action for Childhood Arrivals": "Utah",
      "__EMPTY": 13081,
      "__EMPTY_1": 46533,
      "__EMPTY_2": 59614,
      "__EMPTY_3": 10805,
      "__EMPTY_4": 45663,
      "__EMPTY_5": 56468
    },
    {
      "Number of Form I-821D, Consideration of Deferred Action for Childhood Arrivals": "Maryland",
      "__EMPTY": 12715,
      "__EMPTY_1": 43536,
      "__EMPTY_2": 56251,
      "__EMPTY_3": 9991,
      "__EMPTY_4": 42779,
      "__EMPTY_5": 52770
    },
    {
      "Number of Form I-821D, Consideration of Deferred Action for Childhood Arrivals": "Tennessee",
      "__EMPTY": 11544,
      "__EMPTY_1": 41178,
      "__EMPTY_2": 52722,
      "__EMPTY_3": 9218,
      "__EMPTY_4": 40350,
      "__EMPTY_5": 49568
    },
    {
      "Number of Form I-821D, Consideration of Deferred Action for Childhood Arrivals": "Wisconsin",
      "__EMPTY": 9679,
      "__EMPTY_1": 35166,
      "__EMPTY_2": 44845,
      "__EMPTY_3": 8281,
      "__EMPTY_4": 34605,
      "__EMPTY_5": 42886
    },
    {
      "Number of Form I-821D, Consideration of Deferred Action for Childhood Arrivals": "Oklahoma",
      "__EMPTY": 9385,
      "__EMPTY_1": 33558,
      "__EMPTY_2": 42943,
      "__EMPTY_3": 7599,
      "__EMPTY_4": 32978,
      "__EMPTY_5": 40577
    },
    {
      "Number of Form I-821D, Consideration of Deferred Action for Childhood Arrivals": "South Carolina",
      "__EMPTY": 8752,
      "__EMPTY_1": 31607,
      "__EMPTY_2": 40359,
      "__EMPTY_3": 7050,
      "__EMPTY_4": 31029,
      "__EMPTY_5": 38079
    },
    {
      "Number of Form I-821D, Consideration of Deferred Action for Childhood Arrivals": "Massachusetts",
      "__EMPTY": 9562,
      "__EMPTY_1": 29951,
      "__EMPTY_2": 39513,
      "__EMPTY_3": 7720,
      "__EMPTY_4": 29447,
      "__EMPTY_5": 37167
    },
    {
      "Number of Form I-821D, Consideration of Deferred Action for Childhood Arrivals": "Kansas",
      "__EMPTY": 8634,
      "__EMPTY_1": 29773,
      "__EMPTY_2": 38407,
      "__EMPTY_3": 7396,
      "__EMPTY_4": 29227,
      "__EMPTY_5": 36623
    },
    {
      "Number of Form I-821D, Consideration of Deferred Action for Childhood Arrivals": "New Mexico",
      "__EMPTY": 9371,
      "__EMPTY_1": 29033,
      "__EMPTY_2": 38404,
      "__EMPTY_3": 7716,
      "__EMPTY_4": 28606,
      "__EMPTY_5": 36322
    },
    {
      "Number of Form I-821D, Consideration of Deferred Action for Childhood Arrivals": "Michigan",
      "__EMPTY": 7823,
      "__EMPTY_1": 28754,
      "__EMPTY_2": 36577,
      "__EMPTY_3": 6495,
      "__EMPTY_4": 28245,
      "__EMPTY_5": 34740
    },
    {
      "Number of Form I-821D, Consideration of Deferred Action for Childhood Arrivals": "Minnesota",
      "__EMPTY": 7668,
      "__EMPTY_1": 28508,
      "__EMPTY_2": 36176,
      "__EMPTY_3": 6559,
      "__EMPTY_4": 27890,
      "__EMPTY_5": 34449
    },
    {
      "Number of Form I-821D, Consideration of Deferred Action for Childhood Arrivals": "Pennsylvania",
      "__EMPTY": 7427,
      "__EMPTY_1": 25124,
      "__EMPTY_2": 32551,
      "__EMPTY_3": 5754,
      "__EMPTY_4": 24684,
      "__EMPTY_5": 30438
    },
    {
      "Number of Form I-821D, Consideration of Deferred Action for Childhood Arrivals": "Arkansas",
      "__EMPTY": 6741,
      "__EMPTY_1": 24650,
      "__EMPTY_2": 31391,
      "__EMPTY_3": 5526,
      "__EMPTY_4": 24165,
      "__EMPTY_5": 29691
    },
    {
      "Number of Form I-821D, Consideration of Deferred Action for Childhood Arrivals": "Alabama",
      "__EMPTY": 6163,
      "__EMPTY_1": 21416,
      "__EMPTY_2": 27579,
      "__EMPTY_3": 4806,
      "__EMPTY_4": 21039,
      "__EMPTY_5": 25845
    },
    {
      "Number of Form I-821D, Consideration of Deferred Action for Childhood Arrivals": "Ohio",
      "__EMPTY": 5983,
      "__EMPTY_1": 21341,
      "__EMPTY_2": 27324,
      "__EMPTY_3": 4687,
      "__EMPTY_4": 20915,
      "__EMPTY_5": 25602
    },
    {
      "Number of Form I-821D, Consideration of Deferred Action for Childhood Arrivals": "Connecticut",
      "__EMPTY": 6088,
      "__EMPTY_1": 19791,
      "__EMPTY_2": 25879,
      "__EMPTY_3": 4953,
      "__EMPTY_4": 19477,
      "__EMPTY_5": 24430
    },
    {
      "Number of Form I-821D, Consideration of Deferred Action for Childhood Arrivals": "Missouri",
      "__EMPTY": 4525,
      "__EMPTY_1": 16758,
      "__EMPTY_2": 21283,
      "__EMPTY_3": 3804,
      "__EMPTY_4": 16452,
      "__EMPTY_5": 20256
    },
    {
      "Number of Form I-821D, Consideration of Deferred Action for Childhood Arrivals": "Nebraska",
      "__EMPTY": 4436,
      "__EMPTY_1": 15872,
      "__EMPTY_2": 20308,
      "__EMPTY_3": 3682,
      "__EMPTY_4": 15558,
      "__EMPTY_5": 19240
    },
    {
      "Number of Form I-821D, Consideration of Deferred Action for Childhood Arrivals": "Idaho",
      "__EMPTY": 4200,
      "__EMPTY_1": 15033,
      "__EMPTY_2": 19233,
      "__EMPTY_3": 3421,
      "__EMPTY_4": 14707,
      "__EMPTY_5": 18128
    },
    {
      "Number of Form I-821D, Consideration of Deferred Action for Childhood Arrivals": "Kentucky",
      "__EMPTY": 4135,
      "__EMPTY_1": 14635,
      "__EMPTY_2": 18770,
      "__EMPTY_3": 3310,
      "__EMPTY_4": 14324,
      "__EMPTY_5": 17634
    },
    {
      "Number of Form I-821D, Consideration of Deferred Action for Childhood Arrivals": "Iowa",
      "__EMPTY": 3555,
      "__EMPTY_1": 13577,
      "__EMPTY_2": 17132,
      "__EMPTY_3": 2966,
      "__EMPTY_4": 13339,
      "__EMPTY_5": 16305
    },
    {
      "Number of Form I-821D, Consideration of Deferred Action for Childhood Arrivals": "Louisiana",
      "__EMPTY": 2909,
      "__EMPTY_1": 8997,
      "__EMPTY_2": 11906,
      "__EMPTY_3": 2159,
      "__EMPTY_4": 8811,
      "__EMPTY_5": 10970
    },
    {
      "Number of Form I-821D, Consideration of Deferred Action for Childhood Arrivals": "Mississippi",
      "__EMPTY": 2144,
      "__EMPTY_1": 7012,
      "__EMPTY_2": 9156,
      "__EMPTY_3": 1628,
      "__EMPTY_4": 6907,
      "__EMPTY_5": 8535
    },
    {
      "Number of Form I-821D, Consideration of Deferred Action for Childhood Arrivals": "Delaware",
      "__EMPTY": 1886,
      "__EMPTY_1": 7112,
      "__EMPTY_2": 8998,
      "__EMPTY_3": 1551,
      "__EMPTY_4": 7007,
      "__EMPTY_5": 8558
    },
    {
      "Number of Form I-821D, Consideration of Deferred Action for Childhood Arrivals": "Rhode Island",
      "__EMPTY": 1439,
      "__EMPTY_1": 4863,
      "__EMPTY_2": 6302,
      "__EMPTY_3": 1175,
      "__EMPTY_4": 4779,
      "__EMPTY_5": 5954
    },
    {
      "Number of Form I-821D, Consideration of Deferred Action for Childhood Arrivals": "District Of Columbia",
      "__EMPTY": 990,
      "__EMPTY_1": 3271,
      "__EMPTY_2": 4261,
      "__EMPTY_3": 754,
      "__EMPTY_4": 3218,
      "__EMPTY_5": 3972
    },
    {
      "Number of Form I-821D, Consideration of Deferred Action for Childhood Arrivals": "Wyoming",
      "__EMPTY": 869,
      "__EMPTY_1": 2743,
      "__EMPTY_2": 3612,
      "__EMPTY_3": 673,
      "__EMPTY_4": 2687,
      "__EMPTY_5": 3360
    },
    {
      "Number of Form I-821D, Consideration of Deferred Action for Childhood Arrivals": "Hawaii",
      "__EMPTY": 507,
      "__EMPTY_1": 2130,
      "__EMPTY_2": 2637,
      "__EMPTY_3": 379,
      "__EMPTY_4": 2092,
      "__EMPTY_5": 2471
    },
    {
      "Number of Form I-821D, Consideration of Deferred Action for Childhood Arrivals": "New Hampshire",
      "__EMPTY": 423,
      "__EMPTY_1": 1473,
      "__EMPTY_2": 1896,
      "__EMPTY_3": 336,
      "__EMPTY_4": 1445,
      "__EMPTY_5": 1781
    },
    {
      "Number of Form I-821D, Consideration of Deferred Action for Childhood Arrivals": "South Dakota",
      "__EMPTY": 321,
      "__EMPTY_1": 1213,
      "__EMPTY_2": 1534,
      "__EMPTY_3": 256,
      "__EMPTY_4": 1176,
      "__EMPTY_5": 1432
    },
    {
      "Number of Form I-821D, Consideration of Deferred Action for Childhood Arrivals": "North Dakota",
      "__EMPTY": 123,
      "__EMPTY_1": 795,
      "__EMPTY_2": 918,
      "__EMPTY_3": 83,
      "__EMPTY_4": 785,
      "__EMPTY_5": 868
    },
    {
      "Number of Form I-821D, Consideration of Deferred Action for Childhood Arrivals": "West Virginia",
      "__EMPTY": 176,
      "__EMPTY_1": 726,
      "__EMPTY_2": 902,
      "__EMPTY_3": 123,
      "__EMPTY_4": 702,
      "__EMPTY_5": 825
    },
    {
      "Number of Form I-821D, Consideration of Deferred Action for Childhood Arrivals": "Puerto Rico",
      "__EMPTY": 293,
      "__EMPTY_1": 424,
      "__EMPTY_2": 717,
      "__EMPTY_3": 167,
      "__EMPTY_4": 419,
      "__EMPTY_5": 586
    },
    {
      "Number of Form I-821D, Consideration of Deferred Action for Childhood Arrivals": "Montana",
      "__EMPTY": 89,
      "__EMPTY_1": 532,
      "__EMPTY_2": 621,
      "__EMPTY_3": 68,
      "__EMPTY_4": 521,
      "__EMPTY_5": 589
    },
    {
      "Number of Form I-821D, Consideration of Deferred Action for Childhood Arrivals": "Alaska",
      "__EMPTY": 109,
      "__EMPTY_1": 473,
      "__EMPTY_2": 582,
      "__EMPTY_3": 93,
      "__EMPTY_4": 463,
      "__EMPTY_5": 556
    },
    {
      "Number of Form I-821D, Consideration of Deferred Action for Childhood Arrivals": "Maine",
      "__EMPTY": 63,
      "__EMPTY_1": 348,
      "__EMPTY_2": 411,
      "__EMPTY_3": 49,
      "__EMPTY_4": 343,
      "__EMPTY_5": 392
    },
    {
      "Number of Form I-821D, Consideration of Deferred Action for Childhood Arrivals": "Virgin Islands",
      "__EMPTY": 134,
      "__EMPTY_1": 172,
      "__EMPTY_2": 306,
      "__EMPTY_3": 69,
      "__EMPTY_4": 168,
      "__EMPTY_5": 237
    },
    {
      "Number of Form I-821D, Consideration of Deferred Action for Childhood Arrivals": "Vermont",
      "__EMPTY": 21,
      "__EMPTY_1": 188,
      "__EMPTY_2": 209,
      "__EMPTY_3": 12,
      "__EMPTY_4": 179,
      "__EMPTY_5": 191
    },
    {
      "Number of Form I-821D, Consideration of Deferred Action for Childhood Arrivals": "Armed Forces In The Americas Excluding Canada",
      "__EMPTY": 18,
      "__EMPTY_1": 146,
      "__EMPTY_2": 164,
      "__EMPTY_3": 12,
      "__EMPTY_4": 143,
      "__EMPTY_5": 155
    },
    {
      "Number of Form I-821D, Consideration of Deferred Action for Childhood Arrivals": "Guam",
      "__EMPTY": 25,
      "__EMPTY_1": 101,
      "__EMPTY_2": 126,
      "__EMPTY_3": 21,
      "__EMPTY_4": 97,
      "__EMPTY_5": 118
    },
    {
      "Number of Form I-821D, Consideration of Deferred Action for Childhood Arrivals": "Northern Marianas Island",
      "__EMPTY": 34,
      "__EMPTY_1": 34,
      "__EMPTY_2": 68,
      "__EMPTY_3": 7,
      "__EMPTY_4": 32,
      "__EMPTY_5": 39
    },
    {
      "Number of Form I-821D, Consideration of Deferred Action for Childhood Arrivals": "Armed Forces In Europe, The Middle East, Africa, And Canada",
      "__EMPTY": 2,
      "__EMPTY_1": 35,
      "__EMPTY_2": 37,
      "__EMPTY_3": 2,
      "__EMPTY_4": 35,
      "__EMPTY_5": 37
    },
    {
      "Number of Form I-821D, Consideration of Deferred Action for Childhood Arrivals": "Federated States Of Micronesia",
      "__EMPTY": 4,
      "__EMPTY_1": 30,
      "__EMPTY_2": 34,
      "__EMPTY_3": 3,
      "__EMPTY_4": 27,
      "__EMPTY_5": 30
    },
    {
      "Number of Form I-821D, Consideration of Deferred Action for Childhood Arrivals": "Armed Forces In The Pacific",
      "__EMPTY": 2,
      "__EMPTY_1": 28,
      "__EMPTY_2": 30,
      "__EMPTY_3": 2,
      "__EMPTY_4": 28,
      "__EMPTY_5": 30
    },
    {
      "Number of Form I-821D, Consideration of Deferred Action for Childhood Arrivals": "American Samoa",
      "__EMPTY": 1,
      "__EMPTY_1": 28,
      "__EMPTY_2": 29,
      "__EMPTY_3": 1,
      "__EMPTY_4": 28,
      "__EMPTY_5": 29
    },
    {
      "Number of Form I-821D, Consideration of Deferred Action for Childhood Arrivals": "Palau",
      "__EMPTY": 0,
      "__EMPTY_1": 26,
      "__EMPTY_2": 26,
      "__EMPTY_3": 0,
      "__EMPTY_4": 26,
      "__EMPTY_5": 26
    },
    {
      "Number of Form I-821D, Consideration of Deferred Action for Childhood Arrivals": "Marshall Islands",
      "__EMPTY": 0,
      "__EMPTY_1": 16,
      "__EMPTY_2": 16,
      "__EMPTY_3": 0,
      "__EMPTY_4": 16,
      "__EMPTY_5": 16
    },
    {
      "Number of Form I-821D, Consideration of Deferred Action for Childhood Arrivals": "Not Reported",
      "__EMPTY": 85,
      "__EMPTY_1": 288,
      "__EMPTY_2": 373,
      "__EMPTY_3": 9,
      "__EMPTY_4": 279,
      "__EMPTY_5": 288
    },
    {
      "Number of Form I-821D, Consideration of Deferred Action for Childhood Arrivals": "Grand Total",
      "__EMPTY": 1022222,
      "__EMPTY_1": 3496203,
      "__EMPTY_2": 4518425,
      "__EMPTY_3": 835093,
      "__EMPTY_4": 3437714,
      "__EMPTY_5": 4272807
    },
    {
      "Number of Form I-821D, Consideration of Deferred Action for Childhood Arrivals": "Table Key",
      "__EMPTY": "",
      "__EMPTY_1": "",
      "__EMPTY_2": "",
      "__EMPTY_3": "",
      "__EMPTY_4": "",
      "__EMPTY_5": ""
    },
    {
      "Number of Form I-821D, Consideration of Deferred Action for Childhood Arrivals": "- Represents zero or rounds to 0.0",
      "__EMPTY": "",
      "__EMPTY_1": "",
      "__EMPTY_2": "",
      "__EMPTY_3": "",
      "__EMPTY_4": "",
      "__EMPTY_5": ""
    },
    {
      "Number of Form I-821D, Consideration of Deferred Action for Childhood Arrivals": "References:",
      "__EMPTY": "",
      "__EMPTY_1": "",
      "__EMPTY_2": "",
      "__EMPTY_3": "",
      "__EMPTY_4": "",
      "__EMPTY_5": ""
    },
    {
      "Number of Form I-821D, Consideration of Deferred Action for Childhood Arrivals": "1 The number of requests accepted to date of the reporting period.",
      "__EMPTY": "",
      "__EMPTY_1": "",
      "__EMPTY_2": "",
      "__EMPTY_3": "",
      "__EMPTY_4": "",
      "__EMPTY_5": ""
    },
    {
      "Number of Form I-821D, Consideration of Deferred Action for Childhood Arrivals": "2  The number of requests approved to date of the reporting period.",
      "__EMPTY": "",
      "__EMPTY_1": "",
      "__EMPTY_2": "",
      "__EMPTY_3": "",
      "__EMPTY_4": "",
      "__EMPTY_5": ""
    },
    {
      "Number of Form I-821D, Consideration of Deferred Action for Childhood Arrivals": "3  All fields with a blank in the State field are included in the field \"not reported.\"",
      "__EMPTY": "",
      "__EMPTY_1": "",
      "__EMPTY_2": "",
      "__EMPTY_3": "",
      "__EMPTY_4": "",
      "__EMPTY_5": ""
    },
    {
      "Number of Form I-821D, Consideration of Deferred Action for Childhood Arrivals": "Notes:",
      "__EMPTY": "",
      "__EMPTY_1": "",
      "__EMPTY_2": "",
      "__EMPTY_3": "",
      "__EMPTY_4": "",
      "__EMPTY_5": ""
    },
    {
      "Number of Form I-821D, Consideration of Deferred Action for Childhood Arrivals": "1) Some requests approved may have been received in previous reporting periods. ",
      "__EMPTY": "",
      "__EMPTY_1": "",
      "__EMPTY_2": "",
      "__EMPTY_3": "",
      "__EMPTY_4": "",
      "__EMPTY_5": ""
    },
    {
      "Number of Form I-821D, Consideration of Deferred Action for Childhood Arrivals": "2) The report reflects the most up-to-date estimate data available at the time the report is generated.",
      "__EMPTY": "",
      "__EMPTY_1": "",
      "__EMPTY_2": "",
      "__EMPTY_3": "",
      "__EMPTY_4": "",
      "__EMPTY_5": ""
    },
    {
      "Number of Form I-821D, Consideration of Deferred Action for Childhood Arrivals": "3) Ranked by total approvals.",
      "__EMPTY": "",
      "__EMPTY_1": "",
      "__EMPTY_2": "",
      "__EMPTY_3": "",
      "__EMPTY_4": "",
      "__EMPTY_5": ""
    },
    {
      "Number of Form I-821D, Consideration of Deferred Action for Childhood Arrivals": "4) For a complete list of USCIS forms and descriptions, visit: https://www.uscis.gov/forms",
      "__EMPTY": "",
      "__EMPTY_1": "",
      "__EMPTY_2": "",
      "__EMPTY_3": "",
      "__EMPTY_4": "",
      "__EMPTY_5": ""
    },
    {
      "Number of Form I-821D, Consideration of Deferred Action for Childhood Arrivals": "Source:",
      "__EMPTY": "",
      "__EMPTY_1": "",
      "__EMPTY_2": "",
      "__EMPTY_3": "",
      "__EMPTY_4": "",
      "__EMPTY_5": ""
    },
    {
      "Number of Form I-821D, Consideration of Deferred Action for Childhood Arrivals": "Department of Homeland Security, U.S. Citizenship and Immigration Services, Office of Performance and Quality",
      "__EMPTY": "",
      "__EMPTY_1": "",
      "__EMPTY_2": "",
      "__EMPTY_3": "",
      "__EMPTY_4": "",
      "__EMPTY_5": ""
    },
    {
      "Number of Form I-821D, Consideration of Deferred Action for Childhood Arrivals": "CLAIMS3, ELIS, accessed 7/2025, PAER0018275",
      "__EMPTY": "",
      "__EMPTY_1": "",
      "__EMPTY_2": "",
      "__EMPTY_3": "",
      "__EMPTY_4": "",
      "__EMPTY_5": ""
    }
  ]
}